Workbook

Sheet README
A1: VietStyle Commerce | Inventory Control Workbook
A2: For inventory policy simulation using Datathon 2026. This is not a production WMS/ERP system.
A4: Item | B4: Content
A5: Data source | B5: datathon-2026-round-1.zip: inventory.csv, products.csv, promotions.csv, returns.csv, orders.csv, sales.csv.
A6: Scope | B6: 2,412 SKUs in products.csv; 60,247 inventory snapshot records; inventory data from 2012-07-31 to 2022-12-31.
A7: Sample snapshot | B7: 2022-12-31 — 424 SKUs have records in the latest snapshot. This does not represent current inventory.
A8: Demand calculation | B8: Avg monthly demand = average units_sold across up to 3 most recent available snapshots for the SKU. These may not be 3 consecutive months.
A9: Assumed parameters | B9: Lead time = 14 days; safety stock = 7 days; review period = 7 days. Adjust by supplier / SKU before use.
A10: ROP | B10: Avg daily demand × (Lead time + Safety days). Avg daily demand = Avg monthly demand / 30.
A11: Target stock | B11: Avg daily demand × (Lead time + Safety days + Review period).
A12: Inventory position | B12: On-hand + Open PO − Backorder. The dataset has no Open PO / Backorder data; the workbook defaults to 0 and requires actual values to be entered.
A13: Stockout signal | B13: stockout_days ≥ 1 or fill_rate < 95% or calculated days of supply ≤ 14 days.
A14: Overstock signal | B14: Calculated days of supply > 120 days. >180 days requires a handling plan under the policy.
A15: Conflict gate | B15: If a stockout signal occurs while calculated days of supply >120 days, set DATA CONFLICT; do not automatically recommend a PO.
... A18: Disclaimer | B18: SIMULATION DOCUMENT FOR DATATHON 2026. Operating thresholds, lead times, KPIs, and approval levels are simulated proposals that must be approved by the business owner before real-world use. The dataset does not clearly specify currency and does not provide inbound PO, warehouse-level inventory, or backorder data. Do not treat sample results as current inventory figures.

Sheet Policy Matrix
A1: Policy Matrix | Thresholds & Responsibilities
A2: The thresholds below are simulation assumptions and require approval before real-world use.
A4: Policy ID | B4: Policy | C4: Trigger | D4: Required action | E4: Owner | F4: SLA / Frequency | G4: Approval
A5: INV-POL-001 | B5: Inventory Data Governance | C5: Any change to SKU, inventory, COGS, or item status | D5: Record the operator, timestamp, before/after values, and reason; never overwrite history | E5: Inventory Controller / Data Owner | F5: Within the day | G5: Required
A6: INV-POL-002 | B6: Replenishment | C6: Inventory position <= reorder point, with no unresolved data alerts | D6: Propose a PO based on target stock; check open POs, backorders, MOQ, and budget before submitting for approval | E6: Planner + Procurement | F6: Review weekly | G6: Per purchasing authority limits
A7: INV-POL-003 | B7: Inventory Conflict Verification | C7: A stockout/low-service signal occurs with >120 days of supply, or stockout and overstock flags are both enabled | D7: Temporarily block automatic POs; check transactions, snapshot, pending orders, and demand calculations | E7: Inventory Controller | F7: P1 within 1 business day | G7: Warehouse Manager approves the conclusion
A8: INV-POL-004 | B8: ABC Cycle Counting | C8: A/B/C SKUs classified by annual consumption value | D8: A: weekly; B: monthly; C: quarterly; use blind counts and independent reconciliation | E8: Warehouse Supervisor | F8: As scheduled | G8: Variances above threshold require approval
A9: INV-POL-005 | B9: Inventory Adjustment | C9: A variance exists between physical count and system quantity | D9: Do not adjust without a report, reason code, and evidence; separate the counter and approver | E9: Warehouse Supervisor + Inventory Controller | F9: Within 1 business day | G9: Large variances require Finance/Operations
A10: INV-POL-006 | B10: Excess / Slow-Moving Inventory | C10: Calculated days of supply >120 days; a handling plan is required above 180 days | D10: Stop replenishment; review transfers, bundles, markdowns, or disposal while protecting margin | E10: Merchandising + Procurement | F10: Review monthly | G10: Markdowns subject to pricing authority
A11: INV-POL-007 | B11: Returned Goods | C11: Customer return received | D11: Quarantine until QA classifies it: A-grade resale; B-grade repair/repack; C-grade damaged or missing accessories handled separately | E11: Returns QA + Warehouse | F11: Within 2 business days | G11: Scrapping/write-offs require approval
A12: INV-POL-008 | B12: Promotion Management | C12: A campaign/promotion is scheduled | D12: Forecast demand at least four weeks ahead; check inventory, lead time, stackable_flag, and discount; finalize the plan after approval | E12: Merchandising + Planner | F12: T-4 weeks | G12: Do not stack promotions unless authorized
A13: INV-POL-009 | B13: Supplier Control | C13: Creating a PO or evaluating a supplier | D13: Maintain actual lead times, MOQ, delivery schedules, and fill/on-time delivery rates; update after each receipt | E13: Procurement | F13: Each receipt / monthly | G13: The 14-day lead time is only a default assumption
A14: INV-POL-010 | B14: Defective / Quarantined Goods | C14: SKU is defective, suspected counterfeit, mislabeled, or involved in a serious discrepancy | D14: Set status to HOLD/QUARANTINE; do not sell or include in available-to-promise until a decision is made | E14: QA + Warehouse Supervisor | F14: Immediately | G14: QA/Operations decides disposition
A15: INV-POL-011 | B15: KPIs and Alerts | C15: Periodic operational reporting | D15: Track fill rate, stockout rate, inventory accuracy, days of supply, aged stock, and PO adherence | E15: Inventory Manager | F15: Weekly/monthly | G15: Metric definitions must be standardized
A16: INV-POL-012 | B16: AI / Automated Reporting | C16: AI Agent generates an answer or PO recommendation | D16: Use only authorized data; cite sources and snapshot date; never create POs or adjust inventory autonomously; escalate conflicts for human approval | E16: System Owner + Inventory Controller | F16: Each request | G16: Human approval required

Sheet Inventory Control
A1: Inventory Control | Snapshot & Reorder Planner
A2: Source snapshot: 2022-12-31. Calculated fields use assumptions documented in the README; verify exceptions before ordering.
A4: Snapshot Date | B4: Product ID | C4: Product Name | D4: Category | E4: Segment | F4: Size | G4: Color | H4: On-hand Units | I4: Units Sold (Latest) | J4: Avg Monthly Demand (3 snapshots) | K4: Avg Daily Demand | L4: Stockout Days | M4: Fill Rate | N4: Source Stockout Flag | O4: Source Overstock Flag | P4: Source Reorder Flag | Q4: Open PO Units (input) | R4: Backorder Units (input) | S4: Inventory Position | T4: Lead Time Days (input) | U4: Safety Days | V4: Review Period Days | W4: Reorder Point (ROP) | X4: Target Stock | Y4: Calculated Days of Supply | Z4: Policy Decision | AA4: Suggested Order Qty | AB4: Priority | AC4: Unit Price (source) | AD4: COGS (source) | AE4: On-hand COGS Value
A5: 2022-12-31 | B5: 1 | C5: DragonWear MA-01 | D5: Casual | E5: All-weather | F5: M | G5: black | H5: 3 | I5: 1 | J5: 1 | K5: =IFERROR(J5/30,0) | L5: 1 | M5: 0.9667 | N5: 1 | O5: 0 | P5: 0 | Q5: 0 | R5: 0 | S5: =H5+Q5-R5 | T5: 14 | U5: 7 | V5: 7 | W5: =K5*(T5+U5) | X5: =K5*(T5+U5+V5) | Y5: =IF(K5>0,H5/K5,99999) | Z5: =IF(AND(OR(L5>=1,M5<0.95),Y5>120),"DATA CONFLICT - VERIFY",IF(OR(L5>=1,M5<0.95,Y5<=14),"SERVICE / STOCKOUT REVIEW",IF(Y5>120,"OVERSTOCK REVIEW",IF(S5<=W5,"REPLENISHMENT REVIEW","NORMAL MONITORING")))) | AA5: =IF(OR(Z5="DATA CONFLICT - VERIFY",Z5="SERVICE / STOCKOUT REVIEW"),0,IF(S5<=W5,MAX(0,ROUNDUP(X5-S5,0)),0)) | AB5: =IF(Z5="DATA CONFLICT - VERIFY","P1 - DATA CONFLICT",IF(Z5="SERVICE / STOCKOUT REVIEW","P1 - SERVICE",IF(Z5="OVERSTOCK REVIEW","P2 - OVERSTOCK",IF(Z5="REPLENISHMENT REVIEW","P2 - REPLENISH","P3 - MONITOR")))) | AC5: 4945.5 | AD5: 2732.8833 | AE5: =IF(OR(AD5="",H5=""),"",H5*AD5)
A6: 2022-12-31 | B6: 3 | C6: DragonWear MA-03 | D6: Casual | E6: All-weather | F6: XL | G6: blue | H6: 151 | I6: 5 | J6: 6.6666667 | K6: =IFERROR(J6/30,0) | L6: 2 | M6: 0.9333 | N6: 1 | O6: 1 | P6: 0 | Q6: 0 | R6: 0 | S6: =H6+Q6-R6 | T6: 14 | U6: 7 | V6: 7 | W6: =K6*(T6+U6) | X6: =K6*(T6+U6+V6) | Y6: =IF(K6>0,H6/K6,99999) | Z6: =IF(AND(OR(L6>=1,M6<0.95),Y6>120),"DATA CONFLICT - VERIFY",IF(OR(L6>=1,M6<0.95,Y6<=14),"SERVICE / STOCKOUT REVIEW",IF(Y6>120,"OVERSTOCK REVIEW",IF(S6<=W6,"REPLENISHMENT REVIEW","NORMAL MONITORING")))) | AA6: =IF(OR(Z6="DATA CONFLICT - VERIFY",Z6="SERVICE / STOCKOUT REVIEW"),0,IF(S6<=W6,MAX(0,ROUNDUP(X6-S6,0)),0)) | AB6: =IF(Z6="DATA CONFLICT - VERIFY","P1 - DATA CONFLICT",IF(Z6="SERVICE / STOCKOUT REVIEW","P1 - SERVICE",IF(Z6="OVERSTOCK REVIEW","P2 - OVERSTOCK",IF(Z6="REPLENISHMENT REVIEW","P2 - REPLENISH","P3 - MONITOR")))) | AC6: 10831.377 | AD6: 10289.808 | AE6: =IF(OR(AD6="",H6=""),"",H6*AD6)
A7: 2022-12-31 | B7: 8 | C7: DragonWear MA-08 | D7: Casual | E7: All-weather | F7: S | G7: pink | H7: 101 | I7: 1 | J7: 1.3333333 | K7: =IFERROR(J7/30,0) | L7: 2 | M7: 0.9333 | N7: 1 | O7: 1 | P7: 0 | Q7: 0 | R7: 0 | S7: =H7+Q7-R7 | T7: 14 | U7: 7 | V7: 7 | W7: =K7*(T7+U7) | X7: =K7*(T7+U7+V7) | Y7: =IF(K7>0,H7/K7,99999) | Z7: =IF(AND(OR(L7>=1,M7<0.95),Y7>120),"DATA CONFLICT - VERIFY",IF(OR(L7>=1,M7<0.95,Y7<=14),"SERVICE / STOCKOUT REVIEW",IF(Y7>120,"OVERSTOCK REVIEW",IF(S7<=W7,"REPLENISHMENT REVIEW","NORMAL MONITORING")))) | AA7: =IF(OR(Z7="DATA CONFLICT - VERIFY",Z7="SERVICE / STOCKOUT REVIEW"),0,IF(S7<=W7,MAX(0,ROUNDUP(X7-S7,0)),0)) | AB7: =IF(Z7="DATA CONFLICT - VERIFY","P1 - DATA CONFLICT",IF(Z7="SERVICE / STOCKOUT REVIEW","P1 - SERVICE",IF(Z7="OVERSTOCK REVIEW","P2 - OVERSTOCK",IF(Z7="REPLENISHMENT REVIEW","P2 - REPLENISH","P3 - MONITOR")))) | AC7: 5353.4484 | AD7: 3709.4044 | AE7: =IF(OR(AD7="",H7=""),"",H7*AD7)
A8: 2022-12-31 | B8: 9 | C8: DragonWear MA-09 | D8: Casual | E8: All-weather | F8: M | G8: yellow | H8: 83 | I8: 6 | J8: 5 | K8: =IFERROR(J8/30,0) | L8: 1 | M8: 0.9667 | N8: 1 | O8: 1 | P8: 0 | Q8: 0 | R8: 0 | S8: =H8+Q8-R8 | T8: 14 | U8: 7 | V8: 7 | W8: =K8*(T8+U8) | X8: =K8*(T8+U8+V8) | Y8: =IF(K8>0,H8/K8,99999) | Z8: =IF(AND(OR(L8>=1,M8<0.95),Y8>120),"DATA CONFLICT - VERIFY",IF(OR(L8>=1,M8<0.95,Y8<=14),"SERVICE / STOCKOUT REVIEW",IF(Y8>120,"OVERSTOCK REVIEW",IF(S8<=W8,"REPLENISHMENT REVIEW","NORMAL MONITORING")))) | AA8: =IF(OR(Z8="DATA CONFLICT - VERIFY",Z8="SERVICE / STOCKOUT REVIEW"),0,IF(S8<=W8,MAX(0,ROUNDUP(X8-S8,0)),0)) | AB8: =IF(Z8="DATA CONFLICT - VERIFY","P1 - DATA CONFLICT",IF(Z8="SERVICE / STOCKOUT REVIEW","P1 - SERVICE",IF(Z8="OVERSTOCK REVIEW","P2 - OVERSTOCK",IF(Z8="REPLENISHMENT REVIEW","P2 - REPLENISH","P3 - MONITOR")))) | AC8: 7077.196 | AD8: 5879.0267 | AE8: =IF(OR(AD8="",H8=""),"",H8*AD8)
A9: 2022-12-31 | B9: 17 | C9: DragonWear MA-17 | D9: Casual | E9: All-weather | F9: M | G9: silver | H9: 28 | I9: 4 | J9: 3 | K9: =IFERROR(J9/30,0) | L9: 0 | M9: 1 | N9: 0 | O9: 1 | P9: 0 | Q9: 0 | R9: 0 | S9: =H9+Q9-R9 | T9: 14 | U9: 7 | V9: 7 | W9: =K9*(T9+U9) | X9: =K9*(T9+U9+V9) | Y9: =IF(K9>0,H9/K9,99999) | Z9: =IF(AND(OR(L9>=1,M9<0.95),Y9>120),"DATA CONFLICT - VERIFY",IF(OR(L9>=1,M9<0.95,Y9<=14),"SERVICE / STOCKOUT REVIEW",IF(Y9>120,"OVERSTOCK REVIEW",IF(S9<=W9,"REPLENISHMENT REVIEW","NORMAL MONITORING")))) | AA9: =IF(OR(Z9="DATA CONFLICT - VERIFY",Z9="SERVICE / STOCKOUT REVIEW"),0,IF(S9<=W9,MAX(0,ROUNDUP(X9-S9,0)),0)) | AB9: =IF(Z9="DATA CONFLICT - VERIFY","P1 - DATA CONFLICT",IF(Z9="SERVICE / STOCKOUT REVIEW","P1 - SERVICE",IF(Z9="OVERSTOCK REVIEW","P2 - OVERSTOCK",IF(Z9="REPLENISHMENT REVIEW","P2 - REPLENISH","P3 - MONITOR")))) | AC9: 4848.1147 | AD9: 4140.29 | AE9: =IF(OR(AD9="",H9=""),"",H9*AD9)
A10: 2022-12-31 | B10: 18 | C10: DragonWear MA-18 | D10: Casual | E10: All-weather | F10: L | G10: pink | H10: 3 | I10: 1 | J10: 1 | K10: =IFERROR(J10/30,0) | L10: 2 | M10: 0.9333 | N10: 1 | O10: 0 | P10: 0 | Q10: 0 | R10: 0 | S10: =H10+Q10-R10 | T10: 14 | U10: 7 | V10: 7 | W10: =K10*(T10+U10) | X10: =K10*(T10+U10+V10) | Y10: =IF(K10>0,H10/K10,99999) | Z10: =IF(AND(OR(L10>=1,M10<0.95),Y10>120),"DATA CONFLICT - VERIFY",IF(OR(L10>=1,M10<0.95,Y10<=14),"SERVICE / STOCKOUT REVIEW",IF(Y10>120,"OVERSTOCK REVIEW",IF(S10<=W10,"REPLENISHMENT REVIEW","NORMAL MONITORING")))) | AA10: =IF(OR(Z10="DATA CONFLICT - VERIFY",Z10="SERVICE / STOCKOUT REVIEW"),0,IF(S10<=W10,MAX(0,ROUNDUP(X10-S10,0)),0)) | AB10: =IF(Z10="DATA CONFLICT - VERIFY","P1 - DATA CONFLICT",IF(Z10="SERVICE / STOCKOUT REVIEW","P1 - SERVICE",IF(Z10="OVERSTOCK REVIEW","P2 - OVERSTOCK",IF(Z10="REPLENISHMENT REVIEW","P2 - REPLENISH","P3 - MONITOR")))) | AC10: 4712.7033 | AD10: 3098.1312 | AE10: =IF(OR(AD10="",H10=""),"",H10*AD10)
A11: 2022-12-31 | B11: 19 | C11: DragonWear MA-19 | D11: Casual | E11: All-weather | F11: XL | G11: yellow | H11: 9 | I11: 3 | J11: 2.3333333 | K11: =IFERROR(J11/30,0) | L11: 0 | M11: 1 | N11: 0 | O11: 0 | P11: 0 | Q11: 0 | R11: 0 | S11: =H11+Q11-R11 | T11: 14 | U11: 7 | V11: 7 | W11: =K11*(T11+U11) | X11: =K11*(T11+U11+V11) | Y11: =IF(K11>0,H11/K11,99999) | Z11: =IF(AND(OR(L11>=1,M11<0.95),Y11>120),"DATA CONFLICT - VERIFY",IF(OR(L11>=1,M11<0.95,Y11<=14),"SERVICE / STOCKOUT REVIEW",IF(Y11>120,"OVERSTOCK REVIEW",IF(S11<=W11,"REPLENISHMENT REVIEW","NORMAL MONITORING")))) | AA11: =IF(OR(Z11="DATA CONFLICT - VERIFY",Z11="SERVICE / STOCKOUT REVIEW"),0,IF(S11<=W11,MAX(0,ROUNDUP(X11-S11,0)),0)) | AB11: =IF(Z11="DATA CONFLICT - VERIFY","P1 - DATA CONFLICT",IF(Z11="SERVICE / STOCKOUT REVIEW","P1 - SERVICE",IF(Z11="OVERSTOCK REVIEW","P2 - OVERSTOCK",IF(Z11="REPLENISHMENT REVIEW","P2 - REPLENISH","P3 - MONITOR")))) | AC11: 4445.5175 | AD11: 4171.6737 | AE11: =IF(OR(AD11="",H11=""),"",H11*AD11)
A12: 2022-12-31 | B12: 26 | C12: DragonWear MA-26 | D12: Casual | E12: All-weather | F12: L | G12: green | H12: 240 | I12: 10 | J12: 9 | K12: =IFERROR(J12/30,0) | L12: 2 | M12: 0.9333 | N12: 1 | O12: 1 | P12: 0 | Q12: 0 | R12: 0 | S12: =H12+Q12-R12 | T12: 14 | U12: 7 | V12: 7 | W12: =K12*(T12+U12) | X12: =K12*(T12+U12+V12) | Y12: =IF(K12>0,H12/K12,99999) | Z12: =IF(AND(OR(L12>=1,M12<0.95),Y12>120),"DATA CONFLICT - VERIFY",IF(OR(L12>=1,M12<0.95,Y12<=14),"SERVICE / STOCKOUT REVIEW",IF(Y12>120,"OVERSTOCK REVIEW",IF(S12<=W12,"REPLENISHMENT REVIEW","NORMAL MONITORING")))) | AA12: =IF(OR(Z12="DATA CONFLICT - VERIFY",Z12="SERVICE / STOCKOUT REVIEW"),0,IF(S12<=W12,MAX(0,ROUNDUP(X12-S12,0)),0)) | AB12: =IF(Z12="DATA CONFLICT - VERIFY","P1 - DATA CONFLICT",IF(Z12="SERVICE / STOCKOUT REVIEW","P1 - SERVICE",IF(Z12="OVERSTOCK REVIEW","P2 - OVERSTOCK",IF(Z12="REPLENISHMENT REVIEW","P2 - REPLENISH","P3 - MONITOR")))) | AC12: 9437.1432 | AD12: 8226.3578 | AE12: =IF(OR(AD12="",H12=""),"",H12*AD12)
A13: 2022-12-31 | B13: 29 | C13: DragonWear MA-29 | D13: Casual | E13: All-weather | F13: M | G13: yellow | H13: 9 | I13: 2 | J13: 1.6666667 | K13: =IFERROR(J13/30,0) | L13: 1 | M13: 0.9667 | N13: 1 | O13: 1 | P13: 0 | Q13: 0 | R13: 0 | S13: =H13+Q13-R13 | T13: 14 | U13: 7 | V13: 7 | W13: =K13*(T13+U13) | X13: =K13*(T13+U13+V13) | Y13: =IF(K13>0,H13/K13,99999) | Z13: =IF(AND(OR(L13>=1,M13<0.95),Y13>120),"DATA CONFLICT - VERIFY",IF(OR(L13>=1,M13<0.95,Y13<=14),"SERVICE / STOCKOUT REVIEW",IF(Y13>120,"OVERSTOCK REVIEW",IF(S13<=W13,"REPLENISHMENT REVIEW","NORMAL MONITORING")))) | AA13: =IF(OR(Z13="DATA CONFLICT - VERIFY",Z13="SERVICE / STOCKOUT REVIEW"),0,IF(S13<=W13,MAX(0,ROUNDUP(X13-S13,0)),0)) | AB13: =IF(Z13="DATA CONFLICT - VERIFY","P1 - DATA CONFLICT",IF(Z13="SERVICE / STOCKOUT REVIEW","P1 - SERVICE",IF(Z13="OVERSTOCK REVIEW","P2 - OVERSTOCK",IF(Z13="REPLENISHMENT REVIEW","P2 - REPLENISH","P3 - MONITOR")))) | AC13: 6293.7 | AD13: 5979.015 | AE13: =IF(OR(AD13="",H13=""),"",H13*AD13)
A14: 2022-12-31 | B14: 45 | C14: DragonWear MA-45 | D14: Casual | E14: All-weather | F14: M | G14: purple | H14: 9 | I14: 3 | J14: 2 | K14: =IFERROR(J14/30,0) | L14: 2 | M14: 0.9333 | N14: 1 | O14: 0 | P14: 0 | Q14: 0 | R14: 0 | S14: =H14+Q14-R14 | T14: 14 | U14: 7 | V14: 7 | W14: =K14*(T14+U14) | X14: =K14*(T14+U14+V14) | Y14: =IF(K14>0,H14/K14,99999) | Z14: =IF(AND(OR(L14>=1,M14<0.95),Y14>120),"DATA CONFLICT - VERIFY",IF(OR(L14>=1,M14<0.95,Y14<=14),"SERVICE / STOCKOUT REVIEW",IF(Y14>120,"OVERSTOCK REVIEW",IF(S14<=W14,"REPLENISHMENT REVIEW","NORMAL MONITORING")))) | AA14: =IF(OR(Z14="DATA CONFLICT - VERIFY",Z14="SERVICE / STOCKOUT REVIEW"),0,IF(S14<=W14,MAX(0,ROUNDUP(X14-S14,0)),0)) | AB14: =IF(Z14="DATA CONFLICT - VERIFY","P1 - DATA CONFLICT",IF(Z14="SERVICE / STOCKOUT REVIEW","P1 - SERVICE",IF(Z14="OVERSTOCK REVIEW","P2 - OVERSTOCK",IF(Z14="REPLENISHMENT REVIEW","P2 - REPLENISH","P3 - MONITOR")))) | AC14: 5669.37 | AD14: 3456.048 | AE14: =IF(OR(AD14="",H14=""),"",H14*AD14)
A15: 2022-12-31 | B15: 702 | C15: HanoiStreet MA-09 | D15: Casual | E15: All-weather | F15: L | G15: orange | H15: 356 | I15: 1 | J15: 3 | K15: =IFERROR(J15/30,0) | L15: 1 | M15: 0.9667 | N15: 1 | O15: 1 | P15: 0 | Q15: 0 | R15: 0 | S15: =H15+Q15-R15 | T15: 14 | U15: 7 | V15: 7 | W15: =K15*(T15+U15) | X15: =K15*(T15+U15+V15) | Y15: =IF(K15>0,H15/K15,99999) | Z15: =IF(AND(OR(L15>=1,M15<0.95),Y15>120),"DATA CONFLICT - VERIFY",IF(OR(L15>=1,M15<0.95,Y15<=14),"SERVICE / STOCKOUT REVIEW",IF(Y15>120,"OVERSTOCK REVIEW",IF(S15<=W15,"REPLENISHMENT REVIEW","NORMAL MONITORING")))) | AA15: =IF(OR(Z15="DATA CONFLICT - VERIFY",Z15="SERVICE / STOCKOUT REVIEW"),0,IF(S15<=W15,MAX(0,ROUNDUP(X15-S15,0)),0)) | AB15: =IF(Z15="DATA CONFLICT - VERIFY","P1 - DATA CONFLICT",IF(Z15="SERVICE / STOCKOUT REVIEW","P1 - SERVICE",IF(Z15="OVERSTOCK REVIEW","P2 - OVERSTOCK",IF(Z15="REPLENISHMENT REVIEW","P2 - REPLENISH","P3 - MONITOR")))) | AC15: 3720.7119 | AD15: 3306.5967 | AE15: =IF(OR(AD15="",H15=""),"",H15*AD15)
A16: 2022-12-31 | B16: 711 | C16: HanoiStreet MA-18 | D16: Casual | E16: All-weather | F16: XL | G16: black | H16: 129 | I16: 25 | J16: 30.333333 | K16: =IFERROR(J16/30,0) | L16: 1 | M16: 0.9667 | N16: 1 | O16: 1 | P16: 0 | Q16: 0 | R16: 0 | S16: =H16+Q16-R16 | T16: 14 | U16: 7 | V16: 7 | W16: =K16*(T16+U16) | X16: =K16*(T16+U16+V16) | Y16: =IF(K16>0,H16/K16,99999) | Z16: =IF(AND(OR(L16>=1,M16<0.95),Y16>120),"DATA CONFLICT - VERIFY",IF(OR(L16>=1,M16<0.95,Y16<=14),"SERVICE / STOCKOUT REVIEW",IF(Y16>120,"OVERSTOCK REVIEW",IF(S16<=W16,"REPLENISHMENT REVIEW","NORMAL MONITORING")))) | AA16: =IF(OR(Z16="DATA CONFLICT - VERIFY",Z16="SERVICE / STOCKOUT REVIEW"),0,IF(S16<=W16,MAX(0,ROUNDUP(X16-S16,0)),0)) | AB16: =IF(Z16="DATA CONFLICT - VERIFY","P1 - DATA CONFLICT",IF(Z16="SERVICE / STOCKOUT REVIEW","P1 - SERVICE",IF(Z16="OVERSTOCK REVIEW","P2 - OVERSTOCK",IF(Z16="REPLENISHMENT REVIEW","P2 - REPLENISH","P3 - MONITOR")))) | AC16: 2900.2152 | AD16: 2181.5418 | AE16: =IF(OR(AD16="",H16=""),"",H16*AD16)
... A428: 2022-12-31 | B428: 2391 | C428: VietMotion UC-39 | D428: Streetwear | E428: Everyday | F428: XL | G428: black | H428: 130 | I428: 1 | J428: 1.3333333 | K428: =IFERROR(J428/30,0) | L428: 2 | M428: 0.9333 | N428: 1 | O428: 1 | P428: 0 | Q428: 0 | R428: 0 | S428: =H428+Q428-R428 | T428: 14 | U428: 7 | V428: 7 | W428: =K428*(T428+U428) | X428: =K428*(T428+U428+V428) | Y428: =IF(K428>0,H428/K428,99999) | Z428: =IF(AND(OR(L428>=1,M428<0.95),Y428>120),"DATA CONFLICT - VERIFY",IF(OR(L428>=1,M428<0.95,Y428<=14),"SERVICE / STOCKOUT REVIEW",IF(Y428>120,"OVERSTOCK REVIEW",IF(S428<=W428,"REPLENISHMENT REVIEW","NORMAL MONITORING")))) | AA428: =IF(OR(Z428="DATA CONFLICT - VERIFY",Z428="SERVICE / STOCKOUT REVIEW"),0,IF(S428<=W428,MAX(0,ROUNDUP(X428-S428,0)),0)) | AB428: =IF(Z428="DATA CONFLICT - VERIFY","P1 - DATA CONFLICT",IF(Z428="SERVICE / STOCKOUT REVIEW","P1 - SERVICE",IF(Z428="OVERSTOCK REVIEW","P2 - OVERSTOCK",IF(Z428="REPLENISHMENT REVIEW","P2 - REPLENISH","P3 - MONITOR")))) | AC428: 9057.2655 | AD428: 8604.4022 | AE428: =IF(OR(AD428="",H428=""),"",H428*AD428)

Sheet KPI Summary
A1: KPI Summary | Data Baseline & Alerts
A2: Source: inventory.csv; latest snapshot = 31/12/2022. Source rates describe the dataset and are not current company KPIs.
A4: Metric | B4: Value | C4: Interpretation / rule
A5: Inventory snapshots | B5: 60247 | C5: From 2012-07-31 to 2022-12-31
A6: Unique product IDs in inventory | B6: 1624 | C6: SKUs with at least one record in inventory.csv
A7: Product master SKUs | B7: 2412 | C7: products.csv
A8: Latest snapshot SKU rows | B8: 424 | C8: Snapshot 2022-12-31
A9: Source stockout_flag rate | B9: 0.67341112 | C9: Rate across all of inventory.csv; definition requires verification
A10: Source overstock_flag rate | B10: 0.76256079 | C10: Rate across all of inventory.csv; definition requires verification
A11: Rows with both source flags | B11: 30495 | C11: stockout_flag=1 and overstock_flag=1 simultaneously
A12: Source reorder_flag total | B12: 0 | C12: In the source data, the total reorder_flag count is 0
A13: Latest snapshot data conflicts (recomputed) | B13: 228 | C13: Stockout/service signal alongside calculated DOS >120 days
A14: Latest snapshot mean fill rate | B14: 0.9612441 | C14: Average fill_rate in the latest snapshot
A17: Latest Snapshot by Category
A18: Category | B18: SKU Count | C18: On-hand Units | D18: Units Sold (Latest) | E18: Mean Fill Rate
A19: Casual | B19: 40 | C19: 4095 | D19: 190 | E19: 0.9608325
A20: GenZ | B20: 44 | C20: 5126 | D20: 199 | E20: 0.97197045
A21: Outdoor | B21: 144 | C21: 49929 | D21: 1797 | E21: 0.95671528
A22: Streetwear | B22: 196 | C22: 45085 | D22: 1379 | E22: 0.96224745
A25: Live formulas from workbook
A26: Calculated decision | B26: Formula value | C26: Interpretation
A27: P1 - Data conflict | B27: =COUNTIF('Inventory Control'!AB5:AB428,"P1 - DATA CONFLICT") | C27: Prioritize verification before ordering
A28: P1 - Service | B28: =COUNTIF('Inventory Control'!AB5:AB428,"P1 - SERVICE") | C28: Stockout / fill rate requires investigation
A29: P2 - Overstock | B29: =COUNTIF('Inventory Control'!AB5:AB428,"P2 - OVERSTOCK") | C29: Stop replenishment and prepare a handling plan
A30: P2 - Replenish | B30: =COUNTIF('Inventory Control'!AB5:AB428,"P2 - REPLENISH") | C30: Propose a PO only after checking inventory position
A31: Suggested order units | B31: =SUM('Inventory Control'!AA5:AA428) | C31: Simulation proposal; excludes actual MOQ / inbound PO / backorder

Sheet Exception Log
A1: Exception Log | First 100 SKUs to Review
A2: Static table calculated from the 2022-12-31 snapshot. Filter by Priority; this does not replace verification in WMS/ERP.
A4: Snapshot Date | B4: Product ID | C4: Product Name | D4: Category | E4: On-hand | F4: Units Sold Latest | G4: Avg Monthly Demand (3 snapshots) | H4: Calculated DOS | I4: Fill Rate | J4: Priority | K4: Review Status
A5: 2022-12-31 | B5: 2212 | C5: VietMotion RP-09 | D5: Outdoor | E5: 848 | F5: 1 | G5: 1 | H5: 25440 | I5: 0.9333 | J5: P1 - DATA CONFLICT | K5: CONFLICT - VERIFY BEFORE PO
A6: 2022-12-31 | B6: 2253 | C6: VietMotion RP-50 | D6: Outdoor | E6: 639 | F6: 2 | G6: 1.6666667 | H6: 11502 | I6: 0.9333 | J6: P1 - DATA CONFLICT | K6: CONFLICT - VERIFY BEFORE PO
A7: 2022-12-31 | B7: 927 | C7: HanoiStreet UE-36 | D7: Streetwear | E7: 1897 | F7: 3 | G7: 9 | H7: 6323.3333 | I7: 0.9333 | J7: P1 - DATA CONFLICT | K7: CONFLICT - VERIFY BEFORE PO
A8: 2022-12-31 | B8: 2239 | C8: VietMotion RP-36 | D8: Outdoor | E8: 412 | F8: 4 | G8: 2 | H8: 6180 | I8: 0.9333 | J8: P1 - DATA CONFLICT | K8: CONFLICT - VERIFY BEFORE PO
A9: 2022-12-31 | B9: 2384 | C9: VietMotion UC-32 | D9: Streetwear | E9: 333 | F9: 2 | G9: 1.6666667 | H9: 5994 | I9: 0.9333 | J9: P1 - DATA CONFLICT | K9: CONFLICT - VERIFY BEFORE PO
A10: 2022-12-31 | B10: 1061 | C10: MekongFit RP-07 | D10: Outdoor | E10: 383 | F10: 3 | G10: 2.3333333 | H10: 4924.2857 | I10: 0.9333 | J10: P1 - DATA CONFLICT | K10: CONFLICT - VERIFY BEFORE PO
A11: 2022-12-31 | B11: 779 | C11: HanoiStreet RP-67 | D11: Outdoor | E11: 688 | F11: 5 | G11: 4.3333333 | H11: 4763.0769 | I11: 0.9333 | J11: P1 - DATA CONFLICT | K11: CONFLICT - VERIFY BEFORE PO
A12: 2022-12-31 | B12: 762 | C12: HanoiStreet RP-50 | D12: Outdoor | E12: 1221 | F12: 13 | G12: 8.3333333 | H12: 4395.6 | I12: 0.9333 | J12: P1 - DATA CONFLICT | K12: CONFLICT - VERIFY BEFORE PO
A13: 2022-12-31 | B13: 939 | C13: HanoiStreet UC-02 | D13: Streetwear | E13: 454 | F13: 2 | G13: 3.3333333 | H13: 4086 | I13: 0.9333 | J13: P1 - DATA CONFLICT | K13: CONFLICT - VERIFY BEFORE PO
A14: 2022-12-31 | B14: 1223 | C14: MekongFit UC-25 | D14: Streetwear | E14: 450 | F14: 2 | G14: 4.3333333 | H14: 3115.3846 | I14: 0.9333 | J14: P1 - DATA CONFLICT | K14: CONFLICT - VERIFY BEFORE PO
A15: 2022-12-31 | B15: 2402 | C15: VietMotion YY-11 | D15: GenZ | E15: 172 | F15: 1 | G15: 1.6666667 | H15: 3096 | I15: 0.9333 | J15: P1 - DATA CONFLICT | K15: CONFLICT - VERIFY BEFORE PO
A16: 2022-12-31 | B16: 2331 | C16: VietMotion UE-05 | D16: Streetwear | E16: 1489 | F16: 10 | G16: 14.666667 | H16: 3045.6818 | I16: 0.9333 | J16: P1 - DATA CONFLICT | K16: CONFLICT - VERIFY BEFORE PO
... A104: 2022-12-31 | B104: 45 | C104: DragonWear MA-45 | D104: Casual | E104: 9 | F104: 3 | G104: 2 | H104: 135 | I104: 0.9333 | J104: P1 - DATA CONFLICT | K104: CONFLICT - VERIFY BEFORE PO
